zicheng/__init__.py
zicheng/data/city_subzone_attr.json
zicheng/zicheng.py
zicheng-0.1.1.dist-info/LICENSE
zicheng-0.1.1.dist-info/WHEEL
zicheng-0.1.1.dist-info/METADATA
zicheng-0.1.1.dist-info/RECORD
