Metadata-Version: 2.1
Name: zicheng
Version: 0.1.1
Summary: zicheng
License: MIT
Author: zicheng
Requires-Python: >=3.8,<4.0
Classifier: License :: OSI Approved :: MIT License
Classifier: Programming Language :: Python :: 3
Classifier: Programming Language :: Python :: 3.10
Classifier: Programming Language :: Python :: 3.8
Classifier: Programming Language :: Python :: 3.9
